aditya_portfolio_cli/__init__.py
aditya_portfolio_cli/main.py
aditya_portfolio_cli-0.0.3.dist-info/METADATA
aditya_portfolio_cli-0.0.3.dist-info/WHEEL
aditya_portfolio_cli-0.0.3.dist-info/entry_points.txt
aditya_portfolio_cli-0.0.3.dist-info/RECORD
