Metadata-Version: 2.4
Name: aditya-portfolio-cli
Version: 0.0.3
Summary: A portfolio that will is not even readable
Author-email: Aditya <adityanaidu1014@gmail.com>
Classifier: License :: OSI Approved :: MIT License
Classifier: Operating System :: OS Independent
Classifier: Programming Language :: Python :: 3
Requires-Python: >=3.7
